excise/__init__.py
excise/list.py
excise/tuple.py
packge01-1.0.dist-info/METADATA
packge01-1.0.dist-info/WHEEL
packge01-1.0.dist-info/top_level.txt
packge01-1.0.dist-info/RECORD
