Metadata-Version: 2.1
Name: packge01
Version: 1.0
Summary: 一个打包案例
Home-page: UNKNOWN
Author: laozhang
Author-email: UNKNOWN
License: UNKNOWN
Platform: UNKNOWN
